.gitignore
Readme.md
setup.py
numpy_alignments/__init__.py
numpy_alignments/command_line_interface.py
numpy_alignments/comparer.py
numpy_alignments/htmlreport.py
numpy_alignments/numpy_alignments.py
numpy_alignments.egg-info/PKG-INFO
numpy_alignments.egg-info/SOURCES.txt
numpy_alignments.egg-info/dependency_links.txt
numpy_alignments.egg-info/entry_points.txt
numpy_alignments.egg-info/not-zip-safe
numpy_alignments.egg-info/requires.txt
numpy_alignments.egg-info/top_level.txt