Metadata-Version: 2.1
Name: numpy-alignments
Version: 0.0.9
Summary: Numpy Alignments
Home-page: http://github.com/ivargr/numpy_alignments
Author: Ivar Grytten
Author-email: 
License: MIT
Classifier: Programming Language :: Python :: 3
